setup.py
Rocket.egg-info/PKG-INFO
Rocket.egg-info/SOURCES.txt
Rocket.egg-info/dependency_links.txt
Rocket.egg-info/entry_points.txt
Rocket.egg-info/requires.txt
Rocket.egg-info/top_level.txt
rocket/__init__.py
rocket/connection.nonblock.py
rocket/connection.py
rocket/listener.py
rocket/main.py
rocket/monitor.py
rocket/threadpool.py
rocket/worker.py
rocket/methods/__init__.py
rocket/methods/fs.py
rocket/methods/wsgi.py