Metadata-Version: 1.0
Name: Rocket
Version: 1.2.3
Summary: Modern, Multi-threaded, Comet-Friendly WSGI Web Server
Home-page: http://www.launchpad.net/rocket
Author: Timothy Farrell
Author-email: tfarrell@owassobible.org
License: MIT License
Platform: UNKNOWN
Classifier: Development Status :: 4 - Beta
Classifier: Intended Audience :: Developers
Classifier: License :: OSI Approved :: MIT License
Classifier: Natural Language :: English
Classifier: Operating System :: OS Independent
Classifier: Programming Language :: Python :: 2.5
Classifier: Programming Language :: Python :: 2.6
Classifier: Programming Language :: Python :: 3
Classifier: Topic :: Internet :: WWW/HTTP :: WSGI :: Server
Classifier: Topic :: Internet :: WWW/HTTP :: HTTP Servers
